disease_classifier/.DS_Store
disease_classifier/__init__.py
disease_classifier/_widget.py
disease_classifier/aid_cv2_dnn.py
disease_classifier/background_program.py
disease_classifier/image_processing.py
disease_classifier/napari.yaml
disease_classifier/UI/.DS_Store
disease_classifier/UI/MyWidget.py
disease_classifier/UI/art.qrc
disease_classifier/UI/art_rc.py
disease_classifier/UI/disease_classifier.py
disease_classifier/UI/disease_classifier.ui
disease_classifier/_tests/__init__.py
disease_classifier/_tests/test_reader.py
disease_classifier/_tests/test_sample_data.py
disease_classifier/_tests/test_widget.py
disease_classifier/_tests/test_writer.py
disease_classifier-0.0.1.dist-info/LICENSE
disease_classifier-0.0.1.dist-info/METADATA
disease_classifier-0.0.1.dist-info/WHEEL
disease_classifier-0.0.1.dist-info/entry_points.txt
disease_classifier-0.0.1.dist-info/top_level.txt
disease_classifier-0.0.1.dist-info/RECORD
