Metadata-Version: 2.1
Name: disease-classifier
Version: 0.0.1
Summary: A disease classifier based on iPAC images.
Home-page: https://github.com/zcqwh/disease-classifier
Author: Chenqi Zhang
Author-email: cqzhang@g.ecc.u-tokyo.ac.jp
License: BSD-3-Clause
Project-URL: Bug Tracker, https://github.com/zcqwh/disease-classifier/issues
Project-URL: Documentation, https://github.com/zcqwh/disease-classifier#README.md
Project-URL: Source Code, https://github.com/zcqwh/disease-classifier
Project-URL: User Support, https://github.com/zcqwh/disease-classifier/issues
Classifier: Development Status :: 2 - Pre-Alpha
Classifier: Intended Audience :: Developers
Classifier: Framework :: napari
Classifier: Topic :: Software Development :: Testing
Classifier: Programming Language :: Python
Classifier: Programming Language :: Python :: 3
Classifier: Programming Language :: Python :: 3.8
Classifier: Programming Language :: Python :: 3.9
Classifier: Programming Language :: Python :: 3.10
Classifier: Operating System :: OS Independent
Classifier: License :: OSI Approved :: BSD License
Requires-Python: >=3.8
License-File: LICENSE
Requires-Dist: numpy
Requires-Dist: magicgui
Requires-Dist: qtpy
Requires-Dist: matplotlib
Requires-Dist: h5py (>=3.6.0)
Requires-Dist: napari (>=0.4.15)
Requires-Dist: numpy (>=1.22.4)
Requires-Dist: opencv-contrib-python-headless (>=4.5.5.64)
Requires-Dist: pytranskit (>=0.2.3)
Requires-Dist: statsmodels (>=0.13.2)
Provides-Extra: testing
Requires-Dist: tox ; extra == 'testing'
Requires-Dist: pytest ; extra == 'testing'
Requires-Dist: pytest-cov ; extra == 'testing'
Requires-Dist: pytest-qt ; extra == 'testing'
Requires-Dist: napari ; extra == 'testing'
Requires-Dist: pyqt5 ; extra == 'testing'
